MANIFEST.in
README.rst
requirements.txt
setup.py
apy/__init__.py
apy/container.py
apy/handler.py
apy/http.py
apy/main.py
apy/testing.py
apy/kernel/__init__.py
apy/kernel/conf.py
apy/kernel/dispatcher.py
apy/kernel/routing.py
apy/kernel/server/__init__.py
apy/kernel/server/base_adapter.py
apy/kernel/server/tornado_adapter.py
stagecoach_apy.egg-info/PKG-INFO
stagecoach_apy.egg-info/SOURCES.txt
stagecoach_apy.egg-info/dependency_links.txt
stagecoach_apy.egg-info/not-zip-safe
stagecoach_apy.egg-info/requires.txt
stagecoach_apy.egg-info/top_level.txt