Metadata-Version: 1.0
Name: stagecoach-apy
Version: 1.1.3
Summary: Python RESTful API Framework
Home-page: https://github.com/stagecoachio/apy
Author: Felix Carmona
Author-email: mail@felixcarmona.com
License: UNKNOWN
Platform: UNKNOWN
